spark_datiofilesystem_tools/__init__.py
spark_datiofilesystem_tools/functions/__init__.py
spark_datiofilesystem_tools/functions/generator.py
spark_datiofilesystem_tools-0.1.7.dist-info/LICENSE
spark_datiofilesystem_tools-0.1.7.dist-info/METADATA
spark_datiofilesystem_tools-0.1.7.dist-info/WHEEL
spark_datiofilesystem_tools-0.1.7.dist-info/top_level.txt
spark_datiofilesystem_tools-0.1.7.dist-info/RECORD
